farmbot/__init__.py
farmbot/main.py
farmbot/state.py
farmbot/functions/__init__.py
farmbot/functions/api.py
farmbot/functions/basic_commands.py
farmbot/functions/broker.py
farmbot/functions/camera.py
farmbot/functions/information.py
farmbot/functions/jobs.py
farmbot/functions/messages.py
farmbot/functions/movements.py
farmbot/functions/peripherals.py
farmbot/functions/resources.py
farmbot/functions/tools.py
farmbot-2.0.11.dist-info/METADATA
farmbot-2.0.11.dist-info/WHEEL
farmbot-2.0.11.dist-info/licenses/LICENSE
farmbot-2.0.11.dist-info/RECORD
