Metadata-Version: 2.4
Name: farmbot
Version: 2.0.11
Summary: FarmBot Python package
Project-URL: homepage, https://github.com/FarmBot/farmbot-py
Project-URL: issues, https://github.com/FarmBot/farmbot-py/issues
Author: FarmBot Inc.
License-File: LICENSE
Keywords: farmbot
Classifier: License :: OSI Approved :: MIT License
Classifier: Operating System :: OS Independent
Classifier: Programming Language :: Python :: 3
Requires-Python: >=3.9
Requires-Dist: paho-mqtt
Requires-Dist: requests
